PySDM/__init__.py
PySDM/builder.py
PySDM/formulae.py
PySDM/particulator.py
PySDM/attributes/__init__.py
PySDM/attributes/chemistry/__init__.py
PySDM/attributes/chemistry/acidity.py
PySDM/attributes/chemistry/concentration.py
PySDM/attributes/chemistry/hydrogen_ion_concentration.py
PySDM/attributes/ice/__init__.py
PySDM/attributes/ice/cooling_rate.py
PySDM/attributes/ice/freezing_temperature.py
PySDM/attributes/ice/immersed_surface_area.py
PySDM/attributes/impl/__init__.py
PySDM/attributes/impl/attribute.py
PySDM/attributes/impl/attribute_registry.py
PySDM/attributes/impl/base_attribute.py
PySDM/attributes/impl/cell_attribute.py
PySDM/attributes/impl/derived_attribute.py
PySDM/attributes/impl/dummy_attribute.py
PySDM/attributes/impl/extensive_attribute.py
PySDM/attributes/impl/intensive_attribute.py
PySDM/attributes/impl/maximum_attribute.py
PySDM/attributes/impl/mole_amount.py
PySDM/attributes/impl/temperature_variation_option_attribute.py
PySDM/attributes/isotopes/__init__.py
PySDM/attributes/isotopes/delta.py
PySDM/attributes/isotopes/moles.py
PySDM/attributes/numerics/__init__.py
PySDM/attributes/numerics/cell_id.py
PySDM/attributes/numerics/cell_origin.py
PySDM/attributes/numerics/position_in_cell.py
PySDM/attributes/physics/__init__.py
PySDM/attributes/physics/area.py
PySDM/attributes/physics/critical_saturation.py
PySDM/attributes/physics/critical_volume.py
PySDM/attributes/physics/dry_radius.py
PySDM/attributes/physics/dry_volume.py
PySDM/attributes/physics/equilibrium_saturation.py
PySDM/attributes/physics/heat.py
PySDM/attributes/physics/hygroscopicity.py
PySDM/attributes/physics/multiplicity.py
PySDM/attributes/physics/radius.py
PySDM/attributes/physics/relative_fall_velocity.py
PySDM/attributes/physics/reynolds_number.py
PySDM/attributes/physics/temperature.py
PySDM/attributes/physics/terminal_velocity.py
PySDM/attributes/physics/volume.py
PySDM/attributes/physics/water_mass.py
PySDM/backends/__init__.py
PySDM/backends/numba.py
pysdm-2.131.dist-info/licenses/LICENSE
pysdm-2.131.dist-info/METADATA
pysdm-2.131.dist-info/WHEEL
pysdm-2.131.dist-info/top_level.txt
pysdm-2.131.dist-info/RECORD
