Metadata-Version: 2.4
Name: pysdm
Version: 2.131
Summary: Pythonic particle-based (super-droplet) warm-rain/aqueous-chemistry cloud microphysics package with box, parcel & 1D/2D prescribed-flow examples in Python, Julia and Matlab
Author-email: "https://github.com/open-atmos/PySDM/graphs/contributors" <sylwester.arabas@agh.edu.pl>
License-Expression: GPL-3.0-only
Project-URL: Tracker, https://github.com/open-atmos/PySDM/issues
Project-URL: Documentation, https://open-atmos.github.io/PySDM
Project-URL: Source, https://github.com/open-atmos/PySDM
Keywords: physics-simulation,monte-carlo-simulation,gpu-computing,atmospheric-modelling,particle-system,numba,thrust,nvrtc,pint,atmospheric-physics
Classifier: Development Status :: 4 - Beta
Classifier: Intended Audience :: Science/Research
Classifier: Operating System :: OS Independent
Classifier: Programming Language :: Python :: 3
Classifier: Topic :: Scientific/Engineering
Classifier: Topic :: Scientific/Engineering :: Atmospheric Science
Classifier: Topic :: Scientific/Engineering :: Mathematics
Classifier: Topic :: Scientific/Engineering :: Physics
Classifier: Topic :: Software Development :: Libraries
Requires-Python: >=3.8
License-File: LICENSE
Requires-Dist: ThrustRTC==0.3.20
Requires-Dist: CURandRTC>=0.1.2
Requires-Dist: numba>=0.51.2
Requires-Dist: numpy
Requires-Dist: Pint
Requires-Dist: chempy
Requires-Dist: scipy
Requires-Dist: pyevtk
Provides-Extra: tests
Requires-Dist: matplotlib; extra == "tests"
Requires-Dist: Pillow; extra == "tests"
Requires-Dist: pytest; extra == "tests"
Requires-Dist: pytest-timeout; extra == "tests"
Requires-Dist: PySDM-examples; extra == "tests"
Requires-Dist: open-atmos-jupyter-utils>=v1.2.0; extra == "tests"
Requires-Dist: PyPartMC; extra == "tests"
Requires-Dist: pyrcel; extra == "tests"
Requires-Dist: jupyter-core<5.0.0; extra == "tests"
Requires-Dist: ipywidgets!=8.0.3; extra == "tests"
Dynamic: license-file
Dynamic: provides-extra
Dynamic: requires-dist
